dnn_models/__init__.py
dnn_models/cnn_models.py
gsfns/__init__.py
gsfns/print_fns.py
gsfns/dnn_models/__init__.py
gsfns/dnn_models/cnn_models.py
gsfns-0.0.3.dist-info/LICENSE
gsfns-0.0.3.dist-info/METADATA
gsfns-0.0.3.dist-info/WHEEL
gsfns-0.0.3.dist-info/top_level.txt
gsfns-0.0.3.dist-info/RECORD
