Metadata-Version: 2.1
Name: gsfns
Version: 0.0.3
Summary: General Support Functions
Home-page: UNKNOWN
Author: datnt
Author-email: nguyentiendat@dongguk.edu
License: UNKNOWN
Platform: UNKNOWN
Classifier: Programming Language :: Python :: 3
Classifier: License :: OSI Approved :: MIT License
Classifier: Operating System :: OS Independent
